<Properties StartupConfiguration="{B4B9E198-EDFB-4DC5-8E5C-E04DE00E33F5}|Default">
  <MonoDevelop.Ide.Workbench ActiveDocument="MBR/Controllers/RealEstateController.cs">
    <Files>
      <File FileName="MBR/Controllers/EmployerController.cs" Line="117" Column="36" />
      <File FileName="MBR/Models/Employee.cs" Line="27" Column="1" />
      <File FileName="MBR/Models/Context.cs" Line="14" Column="22" />
      <File FileName="MBR/Models/InsuranceCustomer.cs" Line="12" Column="41" />
      <File FileName="MBR/Models/InsuranceCallbackURL.cs" Line="6" Column="37" />
      <File FileName="MBR/Models/MunicipalProperty.cs" Line="6" Column="33" />
      <File FileName="MBR/Models/InsuranceProperty.cs" Line="13" Column="40" />
      <File FileName="MBR/Models/RealEstate.cs" Line="11" Column="17" />
      <File FileName="MBR/Controllers/RealEstateController.cs" Line="36" Column="39" />
      <File FileName="MBR/Startup.cs" Line="1" Column="1" />
      <File FileName="MBR/Program.cs" Line="1" Column="1" />
      <File FileName="MBR/appsettings.json" Line="9" Column="17" />
      <File FileName="MBR/appsettings.Development.json" Line="11" Column="1" />
      <File FileName="MBR/Models/RealEstateCallbackURL.cs" Line="12" Column="46" />
      <File FileName="MBR/Models/EmployeeCallbackURL.cs" Line="16" Column="47" />
      <File FileName="MBR/Models/ApplicationUrls.cs" Line="1" Column="1" />
      <File FileName="MBR/Controllers/BrokerController.cs" Line="48" Column="37" />
      <File FileName="MBR/Models/BrokerCustomer.cs" Line="18" Column="1" />
    </Files>
  </MonoDevelop.Ide.Workbench>
  <MonoDevelop.Ide.Workspace ActiveConfiguration="Debug" />
  <MonoDevelop.Ide.DebuggingService.Breakpoints>
    <BreakpointStore />
  </MonoDevelop.Ide.DebuggingService.Breakpoints>
  <MonoDevelop.Ide.DebuggingService.PinnedWatches />
  <MonoDevelop.Ide.ItemProperties.MBR PreferredExecutionTarget="MonoDevelop.Default" />
  <MultiItemStartupConfigurations />
</Properties>